{
  "appId": "easy-print",
  "version": 1,
  "publishes": {
    "events": [
      {
        "name": "incoming_order_registered",
        "entity": "SharedOrder",
        "idempotencyKey": "order:{sourceOrderId}",
        "payloadSchema": {
          "sourceOrderId": "string",
          "sourceBranchId": "string",
          "sourceBranchName": "string",
          "sourceStoreName": "string",
          "customerName": "string",
          "customerPhone": "string",
          "deliveryAddress": "string",
          "totalAmount": "number",
          "operationalDate": "yyyy-MM-dd",
          "status": "RECEIVED"
        }
      },
      {
        "name": "incoming_order_cancelled",
        "entity": "SharedOrder",
        "idempotencyKey": "order-cancel:{sourceOrderId}",
        "payloadSchema": {
          "sourceOrderId": "string",
          "operationalDate": "yyyy-MM-dd",
          "status": "CANCELLED"
        }
      }
    ],
    "state": [
      {
        "name": "pending_incoming_orders",
        "entity": "SharedOrder",
        "mode": "snapshot"
      }
    ]
  },
  "consumes": {
    "commands": [
      {
        "name": "mark_order_as_dispatched",
        "inputSchema": {
          "sourceOrderId": "string",
          "hubRunId": "string",
          "courierName": "string",
          "deliverySequence": "number"
        }
      }
    ],
    "state": [
      {
        "name": "shared_orders",
        "entity": "SharedOrder",
        "scope": "hub"
      }
    ]
  }
}
